odoo10_addon_scheduler_error_mailer-10.0.1.0.0.99.dev6-py2.7-nspkg.pth
odoo/addons/scheduler_error_mailer/README.rst
odoo/addons/scheduler_error_mailer/__init__.py
odoo/addons/scheduler_error_mailer/__manifest__.py
odoo/addons/scheduler_error_mailer/data/ir_cron_email_tpl.xml
odoo/addons/scheduler_error_mailer/demo/ir_cron_demo.xml
odoo/addons/scheduler_error_mailer/i18n/de.po
odoo/addons/scheduler_error_mailer/i18n/es.po
odoo/addons/scheduler_error_mailer/i18n/hr.po
odoo/addons/scheduler_error_mailer/i18n/pt_BR.po
odoo/addons/scheduler_error_mailer/i18n/scheduler_error_mailer.pot
odoo/addons/scheduler_error_mailer/i18n/sl.po
odoo/addons/scheduler_error_mailer/i18n/zh_CN.po
odoo/addons/scheduler_error_mailer/images/scheduler_error_mailer.jpg
odoo/addons/scheduler_error_mailer/models/__init__.py
odoo/addons/scheduler_error_mailer/models/ir_cron.py
odoo/addons/scheduler_error_mailer/static/description/icon.png
odoo/addons/scheduler_error_mailer/views/ir_cron.xml
odoo10_addon_scheduler_error_mailer-10.0.1.0.0.99.dev6.dist-info/DESCRIPTION.rst
odoo10_addon_scheduler_error_mailer-10.0.1.0.0.99.dev6.dist-info/METADATA
odoo10_addon_scheduler_error_mailer-10.0.1.0.0.99.dev6.dist-info/RECORD
odoo10_addon_scheduler_error_mailer-10.0.1.0.0.99.dev6.dist-info/WHEEL
odoo10_addon_scheduler_error_mailer-10.0.1.0.0.99.dev6.dist-info/metadata.json
odoo10_addon_scheduler_error_mailer-10.0.1.0.0.99.dev6.dist-info/namespace_packages.txt
odoo10_addon_scheduler_error_mailer-10.0.1.0.0.99.dev6.dist-info/top_level.txt
